{
  "additional-engine" : {
    "name" : "additional-engine",
    "type" : "movement-bonus-equipment",
    "localised_name" : [
      "equipment-name.additional-engine"
    ],
    "shape" : {
      "width" : 4,
      "height" : 4
    },
    "energy_production" : 0,
    "shield" : 0,
    "energy_per_shield" : 0,
    "energy_consumption" : 1666.6666666667,
    "equipment_categories" : [
      "vehicle-motor"
    ],
    "background_color" : {
      "r" : 0.2549019753933,
      "g" : 0.29803922772408,
      "b" : 0.75686275959015,
      "a" : 1
    }
  },
  "advanced-additional-engine" : {
    "name" : "advanced-additional-engine",
    "type" : "movement-bonus-equipment",
    "localised_name" : [
      "equipment-name.advanced-additional-engine"
    ],
    "shape" : {
      "width" : 4,
      "height" : 4
    },
    "energy_production" : 0,
    "shield" : 0,
    "energy_per_shield" : 0,
    "energy_consumption" : 4166.6666666667,
    "equipment_categories" : [
      "vehicle-motor"
    ],
    "background_color" : {
      "r" : 0.2549019753933,
      "g" : 0.29803922772408,
      "b" : 0.75686275959015,
      "a" : 1
    }
  },
  "advanced-exoskeleton-equipment" : {
    "name" : "advanced-exoskeleton-equipment",
    "type" : "movement-bonus-equipment",
    "localised_name" : [
      "equipment-name.advanced-exoskeleton-equipment"
    ],
    "shape" : {
      "width" : 2,
      "height" : 4
    },
    "energy_production" : 0,
    "shield" : 0,
    "energy_per_shield" : 0,
    "energy_consumption" : 5000,
    "equipment_categories" : [
      "armor"
    ],
    "background_color" : {
      "r" : 0.2549019753933,
      "g" : 0.29803922772408,
      "b" : 0.75686275959015,
      "a" : 1
    }
  },
  "antimatter-reactor-equipment" : {
    "name" : "antimatter-reactor-equipment",
    "type" : "generator-equipment",
    "localised_name" : [
      "equipment-name.antimatter-reactor-equipment"
    ],
    "shape" : {
      "width" : 4,
      "height" : 4
    },
    "energy_production" : 66666.666666667,
    "shield" : 0,
    "energy_per_shield" : 0,
    "energy_consumption" : 0,
    "equipment_categories" : [
      "universal-equipment"
    ],
    "background_color" : {
      "r" : 0.2549019753933,
      "g" : 0.29803922772408,
      "b" : 0.75686275959015,
      "a" : 1
    }
  },
  "battery-equipment" : {
    "name" : "battery-equipment",
    "type" : "battery-equipment",
    "localised_name" : [
      "equipment-name.battery-equipment"
    ],
    "shape" : {
      "width" : 1,
      "height" : 2
    },
    "energy_production" : 0,
    "shield" : 0,
    "energy_per_shield" : 0,
    "energy_consumption" : 0,
    "equipment_categories" : [
      "armor",
      "universal-equipment"
    ],
    "background_color" : {
      "r" : 0.2549019753933,
      "g" : 0.29803922772408,
      "b" : 0.75686275959015,
      "a" : 1
    }
  },
  "battery-mk2-equipment" : {
    "name" : "battery-mk2-equipment",
    "type" : "battery-equipment",
    "localised_name" : [
      "equipment-name.battery-mk2-equipment"
    ],
    "shape" : {
      "width" : 1,
      "height" : 2
    },
    "energy_production" : 0,
    "shield" : 0,
    "energy_per_shield" : 0,
    "energy_consumption" : 0,
    "equipment_categories" : [
      "armor",
      "universal-equipment"
    ],
    "background_color" : {
      "r" : 0.2549019753933,
      "g" : 0.29803922772408,
      "b" : 0.75686275959015,
      "a" : 1
    }
  },
  "battery-mk3-equipment" : {
    "name" : "battery-mk3-equipment",
    "type" : "battery-equipment",
    "localised_name" : [
      "equipment-name.battery-mk3-equipment"
    ],
    "shape" : {
      "width" : 1,
      "height" : 2
    },
    "energy_production" : 0,
    "shield" : 0,
    "energy_per_shield" : 0,
    "energy_consumption" : 0,
    "equipment_categories" : [
      "universal-equipment"
    ],
    "background_color" : {
      "r" : 0.2549019753933,
      "g" : 0.29803922772408,
      "b" : 0.75686275959015,
      "a" : 1
    }
  },
  "big-battery-equipment" : {
    "name" : "big-battery-equipment",
    "type" : "battery-equipment",
    "localised_name" : [
      "equipment-name.big-battery-equipment"
    ],
    "shape" : {
      "width" : 2,
      "height" : 2
    },
    "energy_production" : 0,
    "shield" : 0,
    "energy_per_shield" : 0,
    "energy_consumption" : 0,
    "equipment_categories" : [
      "universal-equipment"
    ],
    "background_color" : {
      "r" : 0.2549019753933,
      "g" : 0.29803922772408,
      "b" : 0.75686275959015,
      "a" : 1
    }
  },
  "big-battery-mk2-equipment" : {
    "name" : "big-battery-mk2-equipment",
    "type" : "battery-equipment",
    "localised_name" : [
      "equipment-name.big-battery-mk2-equipment"
    ],
    "shape" : {
      "width" : 2,
      "height" : 2
    },
    "energy_production" : 0,
    "shield" : 0,
    "energy_per_shield" : 0,
    "energy_consumption" : 0,
    "equipment_categories" : [
      "universal-equipment"
    ],
    "background_color" : {
      "r" : 0.2549019753933,
      "g" : 0.29803922772408,
      "b" : 0.75686275959015,
      "a" : 1
    }
  },
  "big-battery-mk3-equipment" : {
    "name" : "big-battery-mk3-equipment",
    "type" : "battery-equipment",
    "localised_name" : [
      "equipment-name.big-battery-mk3-equipment"
    ],
    "shape" : {
      "width" : 2,
      "height" : 2
    },
    "energy_production" : 0,
    "shield" : 0,
    "energy_per_shield" : 0,
    "energy_consumption" : 0,
    "equipment_categories" : [
      "universal-equipment"
    ],
    "background_color" : {
      "r" : 0.2549019753933,
      "g" : 0.29803922772408,
      "b" : 0.75686275959015,
      "a" : 1
    }
  },
  "big-imersite-solar-panel-equipment" : {
    "name" : "big-imersite-solar-panel-equipment",
    "type" : "solar-panel-equipment",
    "localised_name" : [
      "equipment-name.big-imersite-solar-panel-equipment"
    ],
    "shape" : {
      "width" : 2,
      "height" : 2
    },
    "energy_production" : 6400,
    "shield" : 0,
    "energy_per_shield" : 0,
    "energy_consumption" : 0,
    "equipment_categories" : [
      "universal-equipment"
    ],
    "background_color" : {
      "r" : 0.2549019753933,
      "g" : 0.29803922772408,
      "b" : 0.75686275959015,
      "a" : 1
    }
  },
  "big-solar-panel-equipment" : {
    "name" : "big-solar-panel-equipment",
    "type" : "solar-panel-equipment",
    "localised_name" : [
      "equipment-name.big-solar-panel-equipment"
    ],
    "shape" : {
      "width" : 2,
      "height" : 2
    },
    "energy_production" : 3200,
    "shield" : 0,
    "energy_per_shield" : 0,
    "energy_consumption" : 0,
    "equipment_categories" : [
      "universal-equipment"
    ],
    "background_color" : {
      "r" : 0.2549019753933,
      "g" : 0.29803922772408,
      "b" : 0.75686275959015,
      "a" : 1
    }
  },
  "creative-mod_super-fusion-reactor-equipment" : {
    "name" : "creative-mod_super-fusion-reactor-equipment",
    "type" : "generator-equipment",
    "localised_name" : [
      "equipment-name.creative-mod_super-fusion-reactor-equipment"
    ],
    "shape" : {
      "width" : 1,
      "height" : 1
    },
    "energy_production" : 90000000000000,
    "shield" : 0,
    "energy_per_shield" : 0,
    "energy_consumption" : 0,
    "equipment_categories" : [
      "armor"
    ],
    "background_color" : {
      "r" : 0.2549019753933,
      "g" : 0.29803922772408,
      "b" : 0.75686275959015,
      "a" : 1
    }
  },
  "creative-mod_super-personal-roboport-equipment" : {
    "name" : "creative-mod_super-personal-roboport-equipment",
    "type" : "roboport-equipment",
    "localised_name" : [
      "equipment-name.creative-mod_super-personal-roboport-equipment"
    ],
    "shape" : {
      "width" : 1,
      "height" : 1
    },
    "energy_production" : 0,
    "shield" : 0,
    "energy_per_shield" : 0,
    "energy_consumption" : 0,
    "equipment_categories" : [
      "armor"
    ],
    "background_color" : {
      "r" : 0.2549019753933,
      "g" : 0.29803922772408,
      "b" : 0.75686275959015,
      "a" : 1
    }
  },
  "cyber-potato-equipment" : {
    "name" : "cyber-potato-equipment",
    "type" : "generator-equipment",
    "localised_name" : [
      "equipment-name.cyber-potato-equipment"
    ],
    "shape" : {
      "width" : 4,
      "height" : 4
    },
    "energy_production" : 83333.333333333,
    "shield" : 0,
    "energy_per_shield" : 0,
    "energy_consumption" : 0,
    "equipment_categories" : [
      "universal-equipment"
    ],
    "background_color" : {
      "r" : 0.2549019753933,
      "g" : 0.29803922772408,
      "b" : 0.75686275959015,
      "a" : 1
    }
  },
  "discharge-defense-equipment" : {
    "name" : "discharge-defense-equipment",
    "type" : "active-defense-equipment",
    "localised_name" : [
      "equipment-name.discharge-defense-equipment"
    ],
    "shape" : {
      "width" : 2,
      "height" : 2
    },
    "energy_production" : 0,
    "shield" : 0,
    "energy_per_shield" : 0,
    "energy_consumption" : 0,
    "equipment_categories" : [
      "armor",
      "universal-equipment"
    ],
    "attack_parameters" : {
      "type" : "projectile",
      "range" : 10,
      "min_range" : 0,
      "turn_range" : 1,
      "fire_penalty" : 0,
      "rotate_penalty" : 0,
      "health_penalty" : 0,
      "min_attack_distance" : 10,
      "damage_modifier" : 10,
      "ammo_consumption_modifier" : 1,
      "cooldown" : 150,
      "warmup" : 0,
      "movement_slow_down_factor" : 1,
      "movement_slow_down_cooldown" : 150,
      "ammo_type" : {
        "action" : [
          {
            "type" : "area",
            "action_delivery" : [
              {
                "type" : "instant",
                "target_effects" : [
                  {
                    "type" : "create-sticker",
                    "repeat_count" : 1,
                    "repeat_count_deviation" : 0,
                    "probability" : 1,
                    "affects_target" : false,
                    "show_in_tooltip" : false,
                    "sticker" : "stun-sticker",
                    "trigger_created_entity" : false
                  },
                  {
                    "type" : "push-back",
                    "repeat_count" : 1,
                    "repeat_count_deviation" : 0,
                    "probability" : 1,
                    "affects_target" : false,
                    "show_in_tooltip" : true,
                    "distance" : 4
                  }
                ]
              },
              {
                "type" : "beam",
                "beam" : "electric-beam-no-sound",
                "add_to_shooter" : false,
                "max_length" : 16,
                "duration" : 15,
                "source_offset" : {
                  "x" : 0,
                  "y" : -0.5
                }
              }
            ],
            "entity_flags" : {
              "not-rotatable" : true,
              "placeable-neutral" : true,
              "placeable-player" : true,
              "placeable-enemy" : true,
              "placeable-off-grid" : true,
              "player-creation" : true,
              "building-direction-8-way" : true,
              "filter-directions" : true,
              "fast-replaceable-no-build-while-moving" : true,
              "breaths-air" : true,
              "not-repairable" : true,
              "not-on-map" : true,
              "not-deconstructable" : true,
              "not-blueprintable" : true,
              "hidden" : true,
              "hide-alt-info" : true,
              "fast-replaceable-no-cross-type-while-moving" : true,
              "no-gap-fill-while-building" : true,
              "not-flammable" : true,
              "no-automated-item-removal" : true,
              "no-automated-item-insertion" : true,
              "no-copy-paste" : true,
              "not-selectable-in-game" : true,
              "not-upgradable" : true
            },
            "ignore_collision_condition" : false,
            "collision_mask" : {
              "ground-tile" : true,
              "water-tile" : true,
              "resource-layer" : true,
              "doodad-layer" : true,
              "floor-layer" : true,
              "item-layer" : true,
              "ghost-layer" : true,
              "object-layer" : true,
              "player-layer" : true,
              "train-layer" : true,
              "layer-11" : true,
              "layer-12" : true,
              "layer-13" : true,
              "layer-14" : true,
              "layer-15" : true
            },
            "trigger_target_mask" : {
              "common" : true,
              "ground-unit" : true
            },
            "force" : "enemy",
            "repeat_count" : 1,
            "probability" : 1,
            "radius" : 8,
            "trigger_from_target" : false,
            "target_entities" : true,
            "collision_mode" : "distance-from-collision-box"
          }
        ],
        "target_type" : "entity",
        "clamp_position" : false,
        "category" : "electric",
        "energy_consumption" : 2000000
      },
      "projectile_center" : {
        "x" : 0,
        "y" : 0
      },
      "projectile_creation_distance" : 0.60000002384186
    },
    "background_color" : {
      "r" : 0.75686275959015,
      "g" : 0,
      "b" : 0,
      "a" : 1
    }
  },
  "energy-shield-equipment" : {
    "name" : "energy-shield-equipment",
    "type" : "energy-shield-equipment",
    "localised_name" : [
      "equipment-name.shield-generator-mk1"
    ],
    "shape" : {
      "width" : 2,
      "height" : 2
    },
    "energy_production" : 0,
    "shield" : 50,
    "energy_per_shield" : 20000,
    "energy_consumption" : 4000,
    "equipment_categories" : [
      "armor",
      "universal-equipment"
    ],
    "background_color" : {
      "r" : 0.2549019753933,
      "g" : 0.29803922772408,
      "b" : 0.75686275959015,
      "a" : 1
    }
  },
  "energy-shield-mk2-equipment" : {
    "name" : "energy-shield-mk2-equipment",
    "type" : "energy-shield-equipment",
    "localised_name" : [
      "equipment-name.shield-generator-mk2"
    ],
    "shape" : {
      "width" : 2,
      "height" : 2
    },
    "energy_production" : 0,
    "shield" : 150,
    "energy_per_shield" : 30000,
    "energy_consumption" : 6000,
    "equipment_categories" : [
      "armor",
      "universal-equipment"
    ],
    "background_color" : {
      "r" : 0.2549019753933,
      "g" : 0.29803922772408,
      "b" : 0.75686275959015,
      "a" : 1
    }
  },
  "energy-shield-mk3-equipment" : {
    "name" : "energy-shield-mk3-equipment",
    "type" : "energy-shield-equipment",
    "localised_name" : [
      "equipment-name.shield-generator-mk3"
    ],
    "shape" : {
      "width" : 2,
      "height" : 2
    },
    "energy_production" : 0,
    "shield" : 200,
    "energy_per_shield" : 40000,
    "energy_consumption" : 9000,
    "equipment_categories" : [
      "universal-equipment"
    ],
    "background_color" : {
      "r" : 0.2549019753933,
      "g" : 0.29803922772408,
      "b" : 0.75686275959015,
      "a" : 1
    }
  },
  "energy-shield-mk4-equipment" : {
    "name" : "energy-shield-mk4-equipment",
    "type" : "energy-shield-equipment",
    "localised_name" : [
      "equipment-name.shield-generator-mk4"
    ],
    "shape" : {
      "width" : 2,
      "height" : 2
    },
    "energy_production" : 0,
    "shield" : 300,
    "energy_per_shield" : 50000,
    "energy_consumption" : 13500,
    "equipment_categories" : [
      "universal-equipment"
    ],
    "background_color" : {
      "r" : 0.2549019753933,
      "g" : 0.29803922772408,
      "b" : 0.75686275959015,
      "a" : 1
    }
  },
  "exoskeleton-equipment" : {
    "name" : "exoskeleton-equipment",
    "type" : "movement-bonus-equipment",
    "localised_name" : [
      "equipment-name.exoskeleton-equipment"
    ],
    "shape" : {
      "width" : 2,
      "height" : 4
    },
    "energy_production" : 0,
    "shield" : 0,
    "energy_per_shield" : 0,
    "energy_consumption" : 3333.3333333333,
    "equipment_categories" : [
      "armor"
    ],
    "background_color" : {
      "r" : 0.2549019753933,
      "g" : 0.29803922772408,
      "b" : 0.75686275959015,
      "a" : 1
    }
  },
  "fusion-reactor-equipment" : {
    "name" : "fusion-reactor-equipment",
    "type" : "generator-equipment",
    "localised_name" : [
      "equipment-name.fusion-reactor-equipment"
    ],
    "shape" : {
      "width" : 4,
      "height" : 4
    },
    "energy_production" : 53333.333333333,
    "shield" : 0,
    "energy_per_shield" : 0,
    "energy_consumption" : 0,
    "equipment_categories" : [
      "armor",
      "universal-equipment"
    ],
    "background_color" : {
      "r" : 0.2549019753933,
      "g" : 0.29803922772408,
      "b" : 0.75686275959015,
      "a" : 1
    }
  },
  "imersite-night-vision-equipment" : {
    "name" : "imersite-night-vision-equipment",
    "type" : "night-vision-equipment",
    "localised_name" : [
      "equipment-name.imersite-night-vision-equipment"
    ],
    "shape" : {
      "width" : 1,
      "height" : 1
    },
    "energy_production" : 0,
    "shield" : 0,
    "energy_per_shield" : 0,
    "energy_consumption" : 250,
    "equipment_categories" : [
      "armor"
    ],
    "background_color" : {
      "r" : 0.2549019753933,
      "g" : 0.29803922772408,
      "b" : 0.75686275959015,
      "a" : 1
    }
  },
  "imersite-solar-panel-equipment" : {
    "name" : "imersite-solar-panel-equipment",
    "type" : "solar-panel-equipment",
    "localised_name" : [
      "equipment-name.imersite-solar-panel-equipment"
    ],
    "shape" : {
      "width" : 1,
      "height" : 1
    },
    "energy_production" : 1333.3333333333,
    "shield" : 0,
    "energy_per_shield" : 0,
    "energy_consumption" : 0,
    "equipment_categories" : [
      "universal-equipment"
    ],
    "background_color" : {
      "r" : 0.2549019753933,
      "g" : 0.29803922772408,
      "b" : 0.75686275959015,
      "a" : 1
    }
  },
  "night-vision-equipment" : {
    "name" : "night-vision-equipment",
    "type" : "night-vision-equipment",
    "localised_name" : [
      "equipment-name.night-vision-equipment"
    ],
    "shape" : {
      "width" : 1,
      "height" : 1
    },
    "energy_production" : 0,
    "shield" : 0,
    "energy_per_shield" : 0,
    "energy_consumption" : 166.66666666667,
    "equipment_categories" : [
      "armor"
    ],
    "background_color" : {
      "r" : 0.2549019753933,
      "g" : 0.29803922772408,
      "b" : 0.75686275959015,
      "a" : 1
    }
  },
  "nuclear-reactor-equipment" : {
    "name" : "nuclear-reactor-equipment",
    "type" : "generator-equipment",
    "localised_name" : [
      "equipment-name.nuclear-reactor-equipment"
    ],
    "shape" : {
      "width" : 4,
      "height" : 4
    },
    "energy_production" : 40000,
    "shield" : 0,
    "energy_per_shield" : 0,
    "energy_consumption" : 0,
    "equipment_categories" : [
      "universal-equipment"
    ],
    "background_color" : {
      "r" : 0.2549019753933,
      "g" : 0.29803922772408,
      "b" : 0.75686275959015,
      "a" : 1
    }
  },
  "personal-laser-defense-equipment" : {
    "name" : "personal-laser-defense-equipment",
    "type" : "active-defense-equipment",
    "localised_name" : [
      "equipment-name.personal-sniper-laser-defense-mk1-equipment"
    ],
    "shape" : {
      "width" : 2,
      "height" : 2
    },
    "energy_production" : 0,
    "shield" : 0,
    "energy_per_shield" : 0,
    "energy_consumption" : 0,
    "equipment_categories" : [
      "armor",
      "universal-equipment"
    ],
    "attack_parameters" : {
      "type" : "beam",
      "range" : 30,
      "min_range" : 0,
      "turn_range" : 1,
      "fire_penalty" : 0,
      "rotate_penalty" : 0,
      "health_penalty" : 0,
      "min_attack_distance" : 30,
      "damage_modifier" : 10,
      "ammo_consumption_modifier" : 1,
      "cooldown" : 80,
      "warmup" : 0,
      "movement_slow_down_factor" : 1,
      "movement_slow_down_cooldown" : 80,
      "ammo_type" : {
        "action" : [
          {
            "type" : "direct",
            "action_delivery" : [
              {
                "type" : "instant",
                "target_effects" : [
                  {
                    "type" : "create-entity",
                    "repeat_count" : 1,
                    "repeat_count_deviation" : 0,
                    "probability" : 1,
                    "affects_target" : false,
                    "show_in_tooltip" : false,
                    "entity_name" : "explosion-hit",
                    "offsets" : [
                      {
                        "x" : 0,
                        "y" : 0
                      }
                    ],
                    "offset_deviation" : {
                      "left_top" : {
                        "x" : 0,
                        "y" : 0
                      },
                      "right_bottom" : {
                        "x" : 0,
                        "y" : 0
                      },
                      "orientation" : 0
                    },
                    "trigger_created_entity" : false,
                    "check_buildablity" : false
                  }
                ]
              },
              {
                "type" : "beam",
                "beam" : "laser-beam",
                "add_to_shooter" : true,
                "max_length" : 35,
                "duration" : 40,
                "source_offset" : {
                  "x" : 0,
                  "y" : -1.31439
                }
              }
            ],
            "entity_flags" : {
              "not-rotatable" : true,
              "placeable-neutral" : true,
              "placeable-player" : true,
              "placeable-enemy" : true,
              "placeable-off-grid" : true,
              "player-creation" : true,
              "building-direction-8-way" : true,
              "filter-directions" : true,
              "fast-replaceable-no-build-while-moving" : true,
              "breaths-air" : true,
              "not-repairable" : true,
              "not-on-map" : true,
              "not-deconstructable" : true,
              "not-blueprintable" : true,
              "hidden" : true,
              "hide-alt-info" : true,
              "fast-replaceable-no-cross-type-while-moving" : true,
              "no-gap-fill-while-building" : true,
              "not-flammable" : true,
              "no-automated-item-removal" : true,
              "no-automated-item-insertion" : true,
              "no-copy-paste" : true,
              "not-selectable-in-game" : true,
              "not-upgradable" : true
            },
            "ignore_collision_condition" : false,
            "collision_mask" : {
              "ground-tile" : true,
              "water-tile" : true,
              "resource-layer" : true,
              "doodad-layer" : true,
              "floor-layer" : true,
              "item-layer" : true,
              "ghost-layer" : true,
              "object-layer" : true,
              "player-layer" : true,
              "train-layer" : true,
              "layer-11" : true,
              "layer-12" : true,
              "layer-13" : true,
              "layer-14" : true,
              "layer-15" : true
            },
            "trigger_target_mask" : {
              "common" : true,
              "ground-unit" : true
            },
            "force" : "all",
            "repeat_count" : 1,
            "probability" : 1,
            "filter_enabled" : false
          }
        ],
        "target_type" : "entity",
        "clamp_position" : false,
        "category" : "laser-turret",
        "energy_consumption" : 3000000
      }
    },
    "background_color" : {
      "r" : 0.75686275959015,
      "g" : 0,
      "b" : 0,
      "a" : 1
    }
  },
  "personal-laser-defense-mk2-equipment" : {
    "name" : "personal-laser-defense-mk2-equipment",
    "type" : "active-defense-equipment",
    "localised_name" : [
      "equipment-name.personal-sniper-laser-defense-mk2-equipment"
    ],
    "shape" : {
      "width" : 2,
      "height" : 2
    },
    "energy_production" : 0,
    "shield" : 0,
    "energy_per_shield" : 0,
    "energy_consumption" : 0,
    "equipment_categories" : [
      "universal-equipment"
    ],
    "attack_parameters" : {
      "type" : "beam",
      "range" : 32.5,
      "min_range" : 0,
      "turn_range" : 1,
      "fire_penalty" : 0,
      "rotate_penalty" : 0,
      "health_penalty" : 0,
      "min_attack_distance" : 32.5,
      "damage_modifier" : 15,
      "ammo_consumption_modifier" : 1,
      "cooldown" : 80,
      "warmup" : 0,
      "movement_slow_down_factor" : 1,
      "movement_slow_down_cooldown" : 80,
      "ammo_type" : {
        "action" : [
          {
            "type" : "direct",
            "action_delivery" : [
              {
                "type" : "instant",
                "target_effects" : [
                  {
                    "type" : "create-entity",
                    "repeat_count" : 1,
                    "repeat_count_deviation" : 0,
                    "probability" : 1,
                    "affects_target" : false,
                    "show_in_tooltip" : false,
                    "entity_name" : "explosion-hit",
                    "offsets" : [
                      {
                        "x" : 0,
                        "y" : 0
                      }
                    ],
                    "offset_deviation" : {
                      "left_top" : {
                        "x" : 0,
                        "y" : 0
                      },
                      "right_bottom" : {
                        "x" : 0,
                        "y" : 0
                      },
                      "orientation" : 0
                    },
                    "trigger_created_entity" : false,
                    "check_buildablity" : false
                  }
                ]
              },
              {
                "type" : "beam",
                "beam" : "laser-beam",
                "add_to_shooter" : true,
                "max_length" : 40,
                "duration" : 40,
                "source_offset" : {
                  "x" : 0,
                  "y" : -1.31439
                }
              }
            ],
            "entity_flags" : {
              "not-rotatable" : true,
              "placeable-neutral" : true,
              "placeable-player" : true,
              "placeable-enemy" : true,
              "placeable-off-grid" : true,
              "player-creation" : true,
              "building-direction-8-way" : true,
              "filter-directions" : true,
              "fast-replaceable-no-build-while-moving" : true,
              "breaths-air" : true,
              "not-repairable" : true,
              "not-on-map" : true,
              "not-deconstructable" : true,
              "not-blueprintable" : true,
              "hidden" : true,
              "hide-alt-info" : true,
              "fast-replaceable-no-cross-type-while-moving" : true,
              "no-gap-fill-while-building" : true,
              "not-flammable" : true,
              "no-automated-item-removal" : true,
              "no-automated-item-insertion" : true,
              "no-copy-paste" : true,
              "not-selectable-in-game" : true,
              "not-upgradable" : true
            },
            "ignore_collision_condition" : false,
            "collision_mask" : {
              "ground-tile" : true,
              "water-tile" : true,
              "resource-layer" : true,
              "doodad-layer" : true,
              "floor-layer" : true,
              "item-layer" : true,
              "ghost-layer" : true,
              "object-layer" : true,
              "player-layer" : true,
              "train-layer" : true,
              "layer-11" : true,
              "layer-12" : true,
              "layer-13" : true,
              "layer-14" : true,
              "layer-15" : true
            },
            "trigger_target_mask" : {
              "common" : true,
              "ground-unit" : true
            },
            "force" : "all",
            "repeat_count" : 1,
            "probability" : 1,
            "filter_enabled" : false
          }
        ],
        "target_type" : "entity",
        "clamp_position" : false,
        "category" : "laser-turret",
        "energy_consumption" : 4000000
      }
    },
    "background_color" : {
      "r" : 0.75686275959015,
      "g" : 0,
      "b" : 0,
      "a" : 1
    }
  },
  "personal-laser-defense-mk3-equipment" : {
    "name" : "personal-laser-defense-mk3-equipment",
    "type" : "active-defense-equipment",
    "localised_name" : [
      "equipment-name.personal-sniper-laser-defense-mk3-equipment"
    ],
    "shape" : {
      "width" : 2,
      "height" : 2
    },
    "energy_production" : 0,
    "shield" : 0,
    "energy_per_shield" : 0,
    "energy_consumption" : 0,
    "equipment_categories" : [
      "universal-equipment"
    ],
    "attack_parameters" : {
      "type" : "beam",
      "range" : 35,
      "min_range" : 0,
      "turn_range" : 1,
      "fire_penalty" : 0,
      "rotate_penalty" : 0,
      "health_penalty" : 0,
      "min_attack_distance" : 35,
      "damage_modifier" : 20,
      "ammo_consumption_modifier" : 1,
      "cooldown" : 90,
      "warmup" : 0,
      "movement_slow_down_factor" : 1,
      "movement_slow_down_cooldown" : 90,
      "ammo_type" : {
        "action" : [
          {
            "type" : "direct",
            "action_delivery" : [
              {
                "type" : "instant",
                "target_effects" : [
                  {
                    "type" : "create-entity",
                    "repeat_count" : 1,
                    "repeat_count_deviation" : 0,
                    "probability" : 1,
                    "affects_target" : false,
                    "show_in_tooltip" : false,
                    "entity_name" : "explosion-hit",
                    "offsets" : [
                      {
                        "x" : 0,
                        "y" : 0
                      }
                    ],
                    "offset_deviation" : {
                      "left_top" : {
                        "x" : 0,
                        "y" : 0
                      },
                      "right_bottom" : {
                        "x" : 0,
                        "y" : 0
                      },
                      "orientation" : 0
                    },
                    "trigger_created_entity" : false,
                    "check_buildablity" : false
                  }
                ]
              },
              {
                "type" : "beam",
                "beam" : "laser-beam",
                "add_to_shooter" : true,
                "max_length" : 40,
                "duration" : 40,
                "source_offset" : {
                  "x" : 0,
                  "y" : -1.31439
                }
              }
            ],
            "entity_flags" : {
              "not-rotatable" : true,
              "placeable-neutral" : true,
              "placeable-player" : true,
              "placeable-enemy" : true,
              "placeable-off-grid" : true,
              "player-creation" : true,
              "building-direction-8-way" : true,
              "filter-directions" : true,
              "fast-replaceable-no-build-while-moving" : true,
              "breaths-air" : true,
              "not-repairable" : true,
              "not-on-map" : true,
              "not-deconstructable" : true,
              "not-blueprintable" : true,
              "hidden" : true,
              "hide-alt-info" : true,
              "fast-replaceable-no-cross-type-while-moving" : true,
              "no-gap-fill-while-building" : true,
              "not-flammable" : true,
              "no-automated-item-removal" : true,
              "no-automated-item-insertion" : true,
              "no-copy-paste" : true,
              "not-selectable-in-game" : true,
              "not-upgradable" : true
            },
            "ignore_collision_condition" : false,
            "collision_mask" : {
              "ground-tile" : true,
              "water-tile" : true,
              "resource-layer" : true,
              "doodad-layer" : true,
              "floor-layer" : true,
              "item-layer" : true,
              "ghost-layer" : true,
              "object-layer" : true,
              "player-layer" : true,
              "train-layer" : true,
              "layer-11" : true,
              "layer-12" : true,
              "layer-13" : true,
              "layer-14" : true,
              "layer-15" : true
            },
            "trigger_target_mask" : {
              "common" : true,
              "ground-unit" : true
            },
            "force" : "all",
            "repeat_count" : 1,
            "probability" : 1,
            "filter_enabled" : false
          }
        ],
        "target_type" : "entity",
        "clamp_position" : false,
        "category" : "laser-turret",
        "energy_consumption" : 6000000
      }
    },
    "background_color" : {
      "r" : 0.75686275959015,
      "g" : 0,
      "b" : 0,
      "a" : 1
    }
  },
  "personal-laser-defense-mk4-equipment" : {
    "name" : "personal-laser-defense-mk4-equipment",
    "type" : "active-defense-equipment",
    "localised_name" : [
      "equipment-name.personal-sniper-laser-defense-mk4-equipment"
    ],
    "shape" : {
      "width" : 2,
      "height" : 2
    },
    "energy_production" : 0,
    "shield" : 0,
    "energy_per_shield" : 0,
    "energy_consumption" : 0,
    "equipment_categories" : [
      "universal-equipment"
    ],
    "attack_parameters" : {
      "type" : "beam",
      "range" : 37.5,
      "min_range" : 0,
      "turn_range" : 1,
      "fire_penalty" : 0,
      "rotate_penalty" : 0,
      "health_penalty" : 0,
      "min_attack_distance" : 37.5,
      "damage_modifier" : 25,
      "ammo_consumption_modifier" : 1,
      "cooldown" : 100,
      "warmup" : 0,
      "movement_slow_down_factor" : 1,
      "movement_slow_down_cooldown" : 100,
      "ammo_type" : {
        "action" : [
          {
            "type" : "direct",
            "action_delivery" : [
              {
                "type" : "instant",
                "target_effects" : [
                  {
                    "type" : "create-entity",
                    "repeat_count" : 1,
                    "repeat_count_deviation" : 0,
                    "probability" : 1,
                    "affects_target" : false,
                    "show_in_tooltip" : false,
                    "entity_name" : "explosion-hit",
                    "offsets" : [
                      {
                        "x" : 0,
                        "y" : 0
                      }
                    ],
                    "offset_deviation" : {
                      "left_top" : {
                        "x" : 0,
                        "y" : 0
                      },
                      "right_bottom" : {
                        "x" : 0,
                        "y" : 0
                      },
                      "orientation" : 0
                    },
                    "trigger_created_entity" : false,
                    "check_buildablity" : false
                  }
                ]
              },
              {
                "type" : "beam",
                "beam" : "laser-beam",
                "add_to_shooter" : true,
                "max_length" : 40,
                "duration" : 40,
                "source_offset" : {
                  "x" : 0,
                  "y" : -1.31439
                }
              }
            ],
            "entity_flags" : {
              "not-rotatable" : true,
              "placeable-neutral" : true,
              "placeable-player" : true,
              "placeable-enemy" : true,
              "placeable-off-grid" : true,
              "player-creation" : true,
              "building-direction-8-way" : true,
              "filter-directions" : true,
              "fast-replaceable-no-build-while-moving" : true,
              "breaths-air" : true,
              "not-repairable" : true,
              "not-on-map" : true,
              "not-deconstructable" : true,
              "not-blueprintable" : true,
              "hidden" : true,
              "hide-alt-info" : true,
              "fast-replaceable-no-cross-type-while-moving" : true,
              "no-gap-fill-while-building" : true,
              "not-flammable" : true,
              "no-automated-item-removal" : true,
              "no-automated-item-insertion" : true,
              "no-copy-paste" : true,
              "not-selectable-in-game" : true,
              "not-upgradable" : true
            },
            "ignore_collision_condition" : false,
            "collision_mask" : {
              "ground-tile" : true,
              "water-tile" : true,
              "resource-layer" : true,
              "doodad-layer" : true,
              "floor-layer" : true,
              "item-layer" : true,
              "ghost-layer" : true,
              "object-layer" : true,
              "player-layer" : true,
              "train-layer" : true,
              "layer-11" : true,
              "layer-12" : true,
              "layer-13" : true,
              "layer-14" : true,
              "layer-15" : true
            },
            "trigger_target_mask" : {
              "common" : true,
              "ground-unit" : true
            },
            "force" : "all",
            "repeat_count" : 1,
            "probability" : 1,
            "filter_enabled" : false
          }
        ],
        "target_type" : "entity",
        "clamp_position" : false,
        "category" : "laser-turret",
        "energy_consumption" : 8000000
      }
    },
    "background_color" : {
      "r" : 0.75686275959015,
      "g" : 0,
      "b" : 0,
      "a" : 1
    }
  },
  "personal-roboport-equipment" : {
    "name" : "personal-roboport-equipment",
    "type" : "roboport-equipment",
    "localised_name" : [
      "equipment-name.personal-roboport-equipment"
    ],
    "shape" : {
      "width" : 2,
      "height" : 2
    },
    "energy_production" : 0,
    "shield" : 0,
    "energy_per_shield" : 0,
    "energy_consumption" : 33333.333333333,
    "equipment_categories" : [
      "robot-interaction-equipment"
    ],
    "background_color" : {
      "r" : 0.2549019753933,
      "g" : 0.29803922772408,
      "b" : 0.75686275959015,
      "a" : 1
    }
  },
  "personal-roboport-mk2-equipment" : {
    "name" : "personal-roboport-mk2-equipment",
    "type" : "roboport-equipment",
    "localised_name" : [
      "equipment-name.personal-roboport-mk2-equipment"
    ],
    "shape" : {
      "width" : 2,
      "height" : 2
    },
    "energy_production" : 0,
    "shield" : 0,
    "energy_per_shield" : 0,
    "energy_consumption" : 83333.333333333,
    "equipment_categories" : [
      "robot-interaction-equipment"
    ],
    "background_color" : {
      "r" : 0.2549019753933,
      "g" : 0.29803922772408,
      "b" : 0.75686275959015,
      "a" : 1
    }
  },
  "personal-submachine-laser-defense-mk1-equipment" : {
    "name" : "personal-submachine-laser-defense-mk1-equipment",
    "type" : "active-defense-equipment",
    "localised_name" : [
      "equipment-name.personal-submachine-laser-defense-mk1-equipment"
    ],
    "shape" : {
      "width" : 2,
      "height" : 2
    },
    "energy_production" : 0,
    "shield" : 0,
    "energy_per_shield" : 0,
    "energy_consumption" : 0,
    "equipment_categories" : [
      "universal-equipment"
    ],
    "attack_parameters" : {
      "type" : "beam",
      "range" : 15,
      "min_range" : 0,
      "turn_range" : 1,
      "fire_penalty" : 0,
      "rotate_penalty" : 0,
      "health_penalty" : 0,
      "min_attack_distance" : 15,
      "damage_modifier" : 2,
      "ammo_consumption_modifier" : 1,
      "cooldown" : 6,
      "warmup" : 0,
      "movement_slow_down_factor" : 1,
      "movement_slow_down_cooldown" : 6,
      "ammo_type" : {
        "action" : [
          {
            "type" : "direct",
            "action_delivery" : [
              {
                "type" : "instant",
                "target_effects" : [
                  {
                    "type" : "create-entity",
                    "repeat_count" : 1,
                    "repeat_count_deviation" : 0,
                    "probability" : 1,
                    "affects_target" : false,
                    "show_in_tooltip" : false,
                    "entity_name" : "explosion-hit",
                    "offsets" : [
                      {
                        "x" : 0,
                        "y" : 0
                      }
                    ],
                    "offset_deviation" : {
                      "left_top" : {
                        "x" : 0,
                        "y" : 0
                      },
                      "right_bottom" : {
                        "x" : 0,
                        "y" : 0
                      },
                      "orientation" : 0
                    },
                    "trigger_created_entity" : false,
                    "check_buildablity" : false
                  }
                ]
              },
              {
                "type" : "beam",
                "beam" : "laser-beam",
                "add_to_shooter" : true,
                "max_length" : 16,
                "duration" : 3,
                "source_offset" : {
                  "x" : 0,
                  "y" : -1.31439
                }
              }
            ],
            "entity_flags" : {
              "not-rotatable" : true,
              "placeable-neutral" : true,
              "placeable-player" : true,
              "placeable-enemy" : true,
              "placeable-off-grid" : true,
              "player-creation" : true,
              "building-direction-8-way" : true,
              "filter-directions" : true,
              "fast-replaceable-no-build-while-moving" : true,
              "breaths-air" : true,
              "not-repairable" : true,
              "not-on-map" : true,
              "not-deconstructable" : true,
              "not-blueprintable" : true,
              "hidden" : true,
              "hide-alt-info" : true,
              "fast-replaceable-no-cross-type-while-moving" : true,
              "no-gap-fill-while-building" : true,
              "not-flammable" : true,
              "no-automated-item-removal" : true,
              "no-automated-item-insertion" : true,
              "no-copy-paste" : true,
              "not-selectable-in-game" : true,
              "not-upgradable" : true
            },
            "ignore_collision_condition" : false,
            "collision_mask" : {
              "ground-tile" : true,
              "water-tile" : true,
              "resource-layer" : true,
              "doodad-layer" : true,
              "floor-layer" : true,
              "item-layer" : true,
              "ghost-layer" : true,
              "object-layer" : true,
              "player-layer" : true,
              "train-layer" : true,
              "layer-11" : true,
              "layer-12" : true,
              "layer-13" : true,
              "layer-14" : true,
              "layer-15" : true
            },
            "trigger_target_mask" : {
              "common" : true,
              "ground-unit" : true
            },
            "force" : "all",
            "repeat_count" : 1,
            "probability" : 1,
            "filter_enabled" : false
          }
        ],
        "target_type" : "entity",
        "clamp_position" : false,
        "category" : "laser-turret",
        "energy_consumption" : 200000
      }
    },
    "background_color" : {
      "r" : 0.75686275959015,
      "g" : 0,
      "b" : 0,
      "a" : 1
    }
  },
  "personal-submachine-laser-defense-mk2-equipment" : {
    "name" : "personal-submachine-laser-defense-mk2-equipment",
    "type" : "active-defense-equipment",
    "localised_name" : [
      "equipment-name.personal-submachine-laser-defense-mk2-equipment"
    ],
    "shape" : {
      "width" : 2,
      "height" : 2
    },
    "energy_production" : 0,
    "shield" : 0,
    "energy_per_shield" : 0,
    "energy_consumption" : 0,
    "equipment_categories" : [
      "universal-equipment"
    ],
    "attack_parameters" : {
      "type" : "beam",
      "range" : 18,
      "min_range" : 0,
      "turn_range" : 1,
      "fire_penalty" : 0,
      "rotate_penalty" : 0,
      "health_penalty" : 0,
      "min_attack_distance" : 18,
      "damage_modifier" : 3,
      "ammo_consumption_modifier" : 1,
      "cooldown" : 6,
      "warmup" : 0,
      "movement_slow_down_factor" : 1,
      "movement_slow_down_cooldown" : 6,
      "ammo_type" : {
        "action" : [
          {
            "type" : "direct",
            "action_delivery" : [
              {
                "type" : "instant",
                "target_effects" : [
                  {
                    "type" : "create-entity",
                    "repeat_count" : 1,
                    "repeat_count_deviation" : 0,
                    "probability" : 1,
                    "affects_target" : false,
                    "show_in_tooltip" : false,
                    "entity_name" : "explosion-hit",
                    "offsets" : [
                      {
                        "x" : 0,
                        "y" : 0
                      }
                    ],
                    "offset_deviation" : {
                      "left_top" : {
                        "x" : 0,
                        "y" : 0
                      },
                      "right_bottom" : {
                        "x" : 0,
                        "y" : 0
                      },
                      "orientation" : 0
                    },
                    "trigger_created_entity" : false,
                    "check_buildablity" : false
                  }
                ]
              },
              {
                "type" : "beam",
                "beam" : "laser-beam",
                "add_to_shooter" : true,
                "max_length" : 29,
                "duration" : 3,
                "source_offset" : {
                  "x" : 0,
                  "y" : -1.31439
                }
              }
            ],
            "entity_flags" : {
              "not-rotatable" : true,
              "placeable-neutral" : true,
              "placeable-player" : true,
              "placeable-enemy" : true,
              "placeable-off-grid" : true,
              "player-creation" : true,
              "building-direction-8-way" : true,
              "filter-directions" : true,
              "fast-replaceable-no-build-while-moving" : true,
              "breaths-air" : true,
              "not-repairable" : true,
              "not-on-map" : true,
              "not-deconstructable" : true,
              "not-blueprintable" : true,
              "hidden" : true,
              "hide-alt-info" : true,
              "fast-replaceable-no-cross-type-while-moving" : true,
              "no-gap-fill-while-building" : true,
              "not-flammable" : true,
              "no-automated-item-removal" : true,
              "no-automated-item-insertion" : true,
              "no-copy-paste" : true,
              "not-selectable-in-game" : true,
              "not-upgradable" : true
            },
            "ignore_collision_condition" : false,
            "collision_mask" : {
              "ground-tile" : true,
              "water-tile" : true,
              "resource-layer" : true,
              "doodad-layer" : true,
              "floor-layer" : true,
              "item-layer" : true,
              "ghost-layer" : true,
              "object-layer" : true,
              "player-layer" : true,
              "train-layer" : true,
              "layer-11" : true,
              "layer-12" : true,
              "layer-13" : true,
              "layer-14" : true,
              "layer-15" : true
            },
            "trigger_target_mask" : {
              "common" : true,
              "ground-unit" : true
            },
            "force" : "all",
            "repeat_count" : 1,
            "probability" : 1,
            "filter_enabled" : false
          }
        ],
        "target_type" : "entity",
        "clamp_position" : false,
        "category" : "laser-turret",
        "energy_consumption" : 350000
      }
    },
    "background_color" : {
      "r" : 0.75686275959015,
      "g" : 0,
      "b" : 0,
      "a" : 1
    }
  },
  "personal-submachine-laser-defense-mk3-equipment" : {
    "name" : "personal-submachine-laser-defense-mk3-equipment",
    "type" : "active-defense-equipment",
    "localised_name" : [
      "equipment-name.personal-submachine-laser-defense-mk3-equipment"
    ],
    "shape" : {
      "width" : 2,
      "height" : 2
    },
    "energy_production" : 0,
    "shield" : 0,
    "energy_per_shield" : 0,
    "energy_consumption" : 0,
    "equipment_categories" : [
      "universal-equipment"
    ],
    "attack_parameters" : {
      "type" : "beam",
      "range" : 20,
      "min_range" : 0,
      "turn_range" : 1,
      "fire_penalty" : 0,
      "rotate_penalty" : 0,
      "health_penalty" : 0,
      "min_attack_distance" : 20,
      "damage_modifier" : 4,
      "ammo_consumption_modifier" : 1,
      "cooldown" : 6,
      "warmup" : 0,
      "movement_slow_down_factor" : 1,
      "movement_slow_down_cooldown" : 6,
      "ammo_type" : {
        "action" : [
          {
            "type" : "direct",
            "action_delivery" : [
              {
                "type" : "instant",
                "target_effects" : [
                  {
                    "type" : "create-entity",
                    "repeat_count" : 1,
                    "repeat_count_deviation" : 0,
                    "probability" : 1,
                    "affects_target" : false,
                    "show_in_tooltip" : false,
                    "entity_name" : "explosion-hit",
                    "offsets" : [
                      {
                        "x" : 0,
                        "y" : 0
                      }
                    ],
                    "offset_deviation" : {
                      "left_top" : {
                        "x" : 0,
                        "y" : 0
                      },
                      "right_bottom" : {
                        "x" : 0,
                        "y" : 0
                      },
                      "orientation" : 0
                    },
                    "trigger_created_entity" : false,
                    "check_buildablity" : false
                  }
                ]
              },
              {
                "type" : "beam",
                "beam" : "laser-beam",
                "add_to_shooter" : true,
                "max_length" : 21,
                "duration" : 3,
                "source_offset" : {
                  "x" : 0,
                  "y" : -1.31439
                }
              }
            ],
            "entity_flags" : {
              "not-rotatable" : true,
              "placeable-neutral" : true,
              "placeable-player" : true,
              "placeable-enemy" : true,
              "placeable-off-grid" : true,
              "player-creation" : true,
              "building-direction-8-way" : true,
              "filter-directions" : true,
              "fast-replaceable-no-build-while-moving" : true,
              "breaths-air" : true,
              "not-repairable" : true,
              "not-on-map" : true,
              "not-deconstructable" : true,
              "not-blueprintable" : true,
              "hidden" : true,
              "hide-alt-info" : true,
              "fast-replaceable-no-cross-type-while-moving" : true,
              "no-gap-fill-while-building" : true,
              "not-flammable" : true,
              "no-automated-item-removal" : true,
              "no-automated-item-insertion" : true,
              "no-copy-paste" : true,
              "not-selectable-in-game" : true,
              "not-upgradable" : true
            },
            "ignore_collision_condition" : false,
            "collision_mask" : {
              "ground-tile" : true,
              "water-tile" : true,
              "resource-layer" : true,
              "doodad-layer" : true,
              "floor-layer" : true,
              "item-layer" : true,
              "ghost-layer" : true,
              "object-layer" : true,
              "player-layer" : true,
              "train-layer" : true,
              "layer-11" : true,
              "layer-12" : true,
              "layer-13" : true,
              "layer-14" : true,
              "layer-15" : true
            },
            "trigger_target_mask" : {
              "common" : true,
              "ground-unit" : true
            },
            "force" : "all",
            "repeat_count" : 1,
            "probability" : 1,
            "filter_enabled" : false
          }
        ],
        "target_type" : "entity",
        "clamp_position" : false,
        "category" : "laser-turret",
        "energy_consumption" : 500000
      }
    },
    "background_color" : {
      "r" : 0.75686275959015,
      "g" : 0,
      "b" : 0,
      "a" : 1
    }
  },
  "personal-submachine-laser-defense-mk4-equipment" : {
    "name" : "personal-submachine-laser-defense-mk4-equipment",
    "type" : "active-defense-equipment",
    "localised_name" : [
      "equipment-name.personal-submachine-laser-defense-mk4-equipment"
    ],
    "shape" : {
      "width" : 2,
      "height" : 2
    },
    "energy_production" : 0,
    "shield" : 0,
    "energy_per_shield" : 0,
    "energy_consumption" : 0,
    "equipment_categories" : [
      "universal-equipment"
    ],
    "attack_parameters" : {
      "type" : "beam",
      "range" : 22,
      "min_range" : 0,
      "turn_range" : 1,
      "fire_penalty" : 0,
      "rotate_penalty" : 0,
      "health_penalty" : 0,
      "min_attack_distance" : 22,
      "damage_modifier" : 7.5,
      "ammo_consumption_modifier" : 1,
      "cooldown" : 6,
      "warmup" : 0,
      "movement_slow_down_factor" : 1,
      "movement_slow_down_cooldown" : 6,
      "ammo_type" : {
        "action" : [
          {
            "type" : "direct",
            "action_delivery" : [
              {
                "type" : "beam",
                "beam" : "laser-beam",
                "add_to_shooter" : true,
                "max_length" : 23,
                "duration" : 3,
                "source_offset" : {
                  "x" : 0,
                  "y" : -1.31439
                }
              }
            ],
            "entity_flags" : {
              "not-rotatable" : true,
              "placeable-neutral" : true,
              "placeable-player" : true,
              "placeable-enemy" : true,
              "placeable-off-grid" : true,
              "player-creation" : true,
              "building-direction-8-way" : true,
              "filter-directions" : true,
              "fast-replaceable-no-build-while-moving" : true,
              "breaths-air" : true,
              "not-repairable" : true,
              "not-on-map" : true,
              "not-deconstructable" : true,
              "not-blueprintable" : true,
              "hidden" : true,
              "hide-alt-info" : true,
              "fast-replaceable-no-cross-type-while-moving" : true,
              "no-gap-fill-while-building" : true,
              "not-flammable" : true,
              "no-automated-item-removal" : true,
              "no-automated-item-insertion" : true,
              "no-copy-paste" : true,
              "not-selectable-in-game" : true,
              "not-upgradable" : true
            },
            "ignore_collision_condition" : false,
            "collision_mask" : {
              "ground-tile" : true,
              "water-tile" : true,
              "resource-layer" : true,
              "doodad-layer" : true,
              "floor-layer" : true,
              "item-layer" : true,
              "ghost-layer" : true,
              "object-layer" : true,
              "player-layer" : true,
              "train-layer" : true,
              "layer-11" : true,
              "layer-12" : true,
              "layer-13" : true,
              "layer-14" : true,
              "layer-15" : true
            },
            "trigger_target_mask" : {
              "common" : true,
              "ground-unit" : true
            },
            "force" : "all",
            "repeat_count" : 1,
            "probability" : 1,
            "filter_enabled" : false
          }
        ],
        "target_type" : "entity",
        "clamp_position" : false,
        "category" : "laser-turret",
        "energy_consumption" : 750000
      }
    },
    "background_color" : {
      "r" : 0.75686275959015,
      "g" : 0,
      "b" : 0,
      "a" : 1
    }
  },
  "portable-generator" : {
    "name" : "portable-generator",
    "type" : "generator-equipment",
    "localised_name" : [
      "equipment-name.portable-generator"
    ],
    "shape" : {
      "width" : 3,
      "height" : 3
    },
    "energy_production" : 9000,
    "shield" : 0,
    "energy_per_shield" : 0,
    "energy_consumption" : 0,
    "equipment_categories" : [
      "universal-equipment"
    ],
    "background_color" : {
      "r" : 0.2549019753933,
      "g" : 0.29803922772408,
      "b" : 0.75686275959015,
      "a" : 1
    }
  },
  "small-portable-generator" : {
    "name" : "small-portable-generator",
    "type" : "generator-equipment",
    "localised_name" : [
      "equipment-name.small-portable-generator"
    ],
    "shape" : {
      "width" : 2,
      "height" : 2
    },
    "energy_production" : 3333.3333333333,
    "shield" : 0,
    "energy_per_shield" : 0,
    "energy_consumption" : 0,
    "equipment_categories" : [
      "universal-equipment"
    ],
    "background_color" : {
      "r" : 0.2549019753933,
      "g" : 0.29803922772408,
      "b" : 0.75686275959015,
      "a" : 1
    }
  },
  "solar-panel-equipment" : {
    "name" : "solar-panel-equipment",
    "type" : "solar-panel-equipment",
    "localised_name" : [
      "equipment-name.solar-panel-equipment"
    ],
    "shape" : {
      "width" : 1,
      "height" : 1
    },
    "energy_production" : 666.66666666667,
    "shield" : 0,
    "energy_per_shield" : 0,
    "energy_consumption" : 0,
    "equipment_categories" : [
      "armor",
      "universal-equipment"
    ],
    "background_color" : {
      "r" : 0.2549019753933,
      "g" : 0.29803922772408,
      "b" : 0.75686275959015,
      "a" : 1
    }
  },
  "superior-exoskeleton-equipment" : {
    "name" : "superior-exoskeleton-equipment",
    "type" : "movement-bonus-equipment",
    "localised_name" : [
      "equipment-name.superior-exoskeleton-equipment"
    ],
    "shape" : {
      "width" : 2,
      "height" : 4
    },
    "energy_production" : 0,
    "shield" : 0,
    "energy_per_shield" : 0,
    "energy_consumption" : 6666.6666666667,
    "equipment_categories" : [
      "armor"
    ],
    "background_color" : {
      "r" : 0.2549019753933,
      "g" : 0.29803922772408,
      "b" : 0.75686275959015,
      "a" : 1
    }
  },
  "vehicle-roboport" : {
    "name" : "vehicle-roboport",
    "type" : "roboport-equipment",
    "localised_name" : [
      "equipment-name.vehicle-roboport"
    ],
    "shape" : {
      "width" : 4,
      "height" : 4
    },
    "energy_production" : 0,
    "shield" : 0,
    "energy_per_shield" : 0,
    "energy_consumption" : 500000,
    "equipment_categories" : [
      "vehicle-robot-interaction-equipment"
    ],
    "background_color" : {
      "r" : 0.2549019753933,
      "g" : 0.29803922772408,
      "b" : 0.75686275959015,
      "a" : 1
    }
  },
  "belt-immunity-equipment" : {
    "name" : "belt-immunity-equipment",
    "type" : "belt-immunity-equipment",
    "localised_name" : [
      "equipment-name.belt-immunity-equipment"
    ],
    "shape" : {
      "width" : 1,
      "height" : 1
    },
    "energy_production" : 0,
    "shield" : 0,
    "energy_per_shield" : 0,
    "energy_consumption" : 1666.6666666667,
    "equipment_categories" : [
      "armor",
      "universal-equipment"
    ],
    "background_color" : {
      "r" : 0.2549019753933,
      "g" : 0.29803922772408,
      "b" : 0.75686275959015,
      "a" : 1
    }
  }
}